{
  "id": "bnx7Dvt2",
  "uuid_num": 66053207314329,
  "metadata": {
    "label": [
      {
        "type": "string",
        "value": "Trois Sonates pour piano et viola da gamba ou violoncelle, composées par J. Seb. Bach. Edition nouvelle, revue, doigtée et enrichie de notes sur l'exécution par Fr. Grützmacher"
      }
    ],
    "description": [
      {
        "type": "string",
        "value": ""
      }
    ],
    "aliases": [],
    "qid": [
      {
        "type": "externalid",
        "value": "",
        "base_url": "http://wwww.wikidata.org/entity/"
      }
    ],
    "object_type": [
      {
        "type": "schema",
        "value": "manifestation"
      }
    ],
    "id": [
      {
        "type": "id",
        "value": "bnx7Dvt2"
      }
    ],
    "nodegoat_id": [
      {
        "type": "id",
        "value": "16005046"
      }
    ],
    "FAAM manifestation ID": [
      {
        "type": "id",
        "value": "BNF-42826443c"
      }
    ],
    "permalink": [
      {
        "type": "url",
        "value": "http://catalogue.bnf.fr/ark:/12148/cb42826443c"
      }
    ],
    "call number": [
      {
        "type": "string",
        "value": "VMG-6571"
      }
    ],
    "score format": [
      {
        "type": "item",
        "value": "XyayZhMR",
        "label": "Full Score"
      },
      {
        "type": "item",
        "value": "guXbuHaq",
        "label": "Parts"
      }
    ],
    "score complexity": [
      {
        "type": "item",
        "value": "WJHHh56W",
        "label": "Mechanical print"
      }
    ]
  },
  "statements": {
    "note": [],
    "sections": [],
    "RISM ID": [],
    "IMSLP ID": [],
    "editorial annotation": [
      {
        "type": "item",
        "value": "2niWvJiL",
        "label": "instrument substitution"
      },
      {
        "type": "item",
        "value": "mkCY9LDD",
        "label": "tempo"
      },
      {
        "type": "item",
        "value": "48ukXYmB",
        "label": "articulation"
      },
      {
        "type": "item",
        "value": "6fQyHcwz",
        "label": "accent"
      },
      {
        "type": "item",
        "value": "K4TocMAK",
        "label": "slur"
      },
      {
        "type": "item",
        "value": "UJ57Ew5y",
        "label": "musical phrasing"
      },
      {
        "type": "item",
        "value": "EXzrp8XT",
        "label": "ossia"
      },
      {
        "type": "item",
        "value": "HKyA3Qzz",
        "label": "dynamic"
      },
      {
        "type": "item",
        "value": "D6RjeTWv",
        "label": "musical expression"
      },
      {
        "type": "item",
        "value": "2qoBxv5j",
        "label": "performance practice"
      },
      {
        "type": "item",
        "value": "j3tnVzW5",
        "label": "diminuendo"
      },
      {
        "type": "item",
        "value": "m9rNaSAR",
        "label": "rallentando"
      },
      {
        "type": "item",
        "value": "JwqBvu9Z",
        "label": "fermata"
      },
      {
        "type": "item",
        "value": "eSzqVmee",
        "label": "crescendo"
      }
    ],
    "handwritten annotation": [],
    "provenance": [
      {
        "type": "item",
        "value": "PRjsXYR5",
        "label": "Bibliothèque Nationale de France"
      }
    ],
    "related item": [],
    "keyword": [
      {
        "type": "item",
        "value": "Gx3B7DJH",
        "label": "early music"
      },
      {
        "type": "item",
        "value": "4Jjg5FwX",
        "label": "string music"
      },
      {
        "type": "item",
        "value": "WiBZjkbR",
        "label": "arrangement"
      },
      {
        "type": "item",
        "value": "gKMU7J89",
        "label": "realization of figured bass"
      }
    ],
    "instrumentation": [
      {
        "type": "item",
        "value": "2nFJpnZ8",
        "label": "cello"
      },
      {
        "type": "item",
        "value": "PyGNLcfw",
        "label": "piano"
      }
    ],
    "musical work": [
      {
        "type": "item",
        "value": "43Adxzby",
        "label": "3 Sonatas for Viola da Gamba and Harpsichord, BWV 1027-1029"
      }
    ],
    "agent": [
      {
        "type": "statement",
        "value": "GecAsFfL",
        "qualifiers": [
          {
            "type": "item",
            "property": "role",
            "value": "YvQmwaaW",
            "label": "composer"
          },
          {
            "type": "item",
            "property": "place",
            "value": ""
          },
          {
            "type": "date",
            "property": "date",
            "value": ""
          }
        ],
        "label": "Johann Sebastian Bach"
      },
      {
        "type": "statement",
        "value": "DVfZGTfW",
        "qualifiers": [
          {
            "type": "item",
            "property": "role",
            "value": "6UPEJgTQ",
            "label": "editor"
          },
          {
            "type": "item",
            "property": "place",
            "value": ""
          },
          {
            "type": "date",
            "property": "date",
            "value": ""
          }
        ],
        "label": "Friedrich Grützmacher"
      },
      {
        "type": "statement",
        "value": "QE9UrJXo",
        "qualifiers": [
          {
            "type": "item",
            "property": "role",
            "value": "7tdgMgre",
            "label": "publisher"
          },
          {
            "type": "item",
            "property": "place",
            "value": "4GU7NjmQ",
            "label": "Leipzig"
          },
          {
            "type": "date",
            "property": "date",
            "value": "1865"
          }
        ],
        "label": "Edition Peters"
      }
    ]
  },
  "cross-references": {},
  "resources": {
    "thumb": [
      {
        "type": "image",
        "value": "BNF-42826443c.gif",
        "base_url": "../assets/images/thumbs/"
      }
    ],
    "GitHub": [
      {
        "type": "url",
        "value": "https://github.com/nicholascornia89/FAAM-editorial_annotations/tree/main/raw-images/BNF-42826443c/"
      }
    ],
    "JSON": [
      {
        "type": "url",
        "base_url": "http://nicholascornia89.github.io/faam/json/",
        "value": "bnx7Dvt2.json"
      }
    ],
    "RDF": [
      {
        "type": "url",
        "base_url": "http://nicholascornia89.github.io/faam/rdf/",
        "value": "bnx7Dvt2.ttl"
      }
    ],
    "CSV": [
      {
        "type": "url",
        "base_url": "http://nicholascornia89.github.io/faam/csv/",
        "value": "bnx7Dvt2.csv"
      }
    ]
  }
}