{
  "id": "DpzzaYow",
  "uuid_num": 23115800916089,
  "metadata": {
    "label": [
      {
        "type": "string",
        "value": "Bormla"
      }
    ],
    "description": [
      {
        "type": "string",
        "value": "city in Malta"
      }
    ],
    "object_type": [
      {
        "type": "schema",
        "value": "city"
      }
    ],
    "id": [
      {
        "type": "id",
        "value": "DpzzaYow"
      }
    ],
    "nodegoat_id": [
      {
        "type": "id",
        "value": "0"
      }
    ],
    "qid": [
      {
        "type": "externalid",
        "value": "Q757225",
        "base_url": "http://wwww.wikidata.org/entity/"
      }
    ],
    "aliases": []
  },
  "statements": {
    "GeoNames ID": []
  },
  "cross-references": {},
  "resources": {}
}