{
  "id": "G5pwZLWh",
  "uuid_num": 27499697350224,
  "metadata": {
    "label": [
      {
        "type": "string",
        "value": "rhapsody"
      },
      {
        "type": "string",
        "value": "rhapsody"
      }
    ],
    "description": [
      {
        "type": "string",
        "value": ""
      },
      {
        "type": "string",
        "value": "musical form"
      }
    ],
    "object_type": [
      {
        "type": "schema",
        "value": "keyword"
      }
    ],
    "id": [
      {
        "type": "id",
        "value": "G5pwZLWh"
      }
    ],
    "nodegoat_id": [
      {
        "type": "id",
        "value": "15990643"
      }
    ],
    "qid": [
      {
        "type": "externalid",
        "value": "Q464769",
        "base_url": "http://wwww.wikidata.org/entity/"
      }
    ],
    "aliases": [
      {
        "type": "string",
        "value": "rhapsody"
      }
    ]
  },
  "statements": {},
  "cross-references": {},
  "resources": {}
}