{
  "id": "GSNsghRd",
  "uuid_num": 28204237889258,
  "metadata": {
    "label": [
      {
        "type": "string",
        "value": "music arranger"
      }
    ],
    "description": [
      {
        "type": "string",
        "value": "musician who creates arrangements"
      }
    ],
    "aliases": [
      {
        "type": "string",
        "value": "arranger"
      },
      {
        "type": "string",
        "value": "musical arranger"
      },
      {
        "type": "string",
        "value": "arranger of music"
      },
      {
        "type": "string",
        "value": "music arranger"
      }
    ],
    "qid": [
      {
        "type": "externalid",
        "value": "Q1643514",
        "base_url": "http://wwww.wikidata.org/entity/",
        "label": "music arranger"
      }
    ],
    "object_type": [
      {
        "type": "schema",
        "value": "occupation"
      }
    ],
    "id": [
      {
        "type": "id",
        "value": "GSNsghRd"
      }
    ],
    "nodegoat_id": [
      {
        "type": "id",
        "value": "15990934"
      }
    ]
  },
  "statements": {},
  "cross-references": {
    "agent": [
      {
        "id": "BiMpVQUM",
        "type": "item",
        "label": "Charles-Marie Widor",
        "description": "French organist and composer (1844–1937)",
        "image": {
          "base_url": "https://commons.wikimedia.org/w/index.php?title=Special:Redirect/file/",
          "value": "Charles-Marie_Widor_(2).jpg"
        }
      },
      {
        "id": "DzFR58ko",
        "type": "item",
        "label": "Franz Görner",
        "description": "German pianist and music arranger",
        "image": {
          "base_url": "https://commons.wikimedia.org/w/index.php?title=Special:Redirect/file/",
          "value": ""
        }
      },
      {
        "id": "AeLkbfSd",
        "type": "item",
        "label": "Willibald Alexis",
        "description": "German historical novelist (1798–1871)",
        "image": {
          "base_url": "https://commons.wikimedia.org/w/index.php?title=Special:Redirect/file/",
          "value": "Willibald_Alexis.jpg"
        }
      },
      {
        "id": "N3dWHyYG",
        "type": "item",
        "label": "Hermann Bäuerle",
        "description": "German theologian and musician",
        "image": {
          "base_url": "https://commons.wikimedia.org/w/index.php?title=Special:Redirect/file/",
          "value": "Hermann_Bäuerle_(1869-1936).jpg"
        }
      },
      {
        "id": "DyTsrwPC",
        "type": "item",
        "label": "Nikolai Rimsky-Korsakov",
        "description": "Russian composer (1844–1908)",
        "image": {
          "base_url": "https://commons.wikimedia.org/w/index.php?title=Special:Redirect/file/",
          "value": "Nikolai_A._Rimsky-Korsakov.jpg"
        }
      },
      {
        "id": "KuMf3k3f",
        "type": "item",
        "label": "Giulio Briccialdi",
        "description": "Italian musician (1818–1881)",
        "image": {
          "base_url": "https://commons.wikimedia.org/w/index.php?title=Special:Redirect/file/",
          "value": "https://upload.wikimedia.org/wikipedia/commons/3/30/Giulio_Baldassarre_Briccialdi_by_Joseph_Kriehuber_%281842%29_-_Archivio_Storico_Ricordi_ICON010461.jpg"
        }
      },
      {
        "id": "Wwj5wpVZ",
        "type": "item",
        "label": "Alfred Lefébure-Wély",
        "description": "French composer and organist (1817–1869)",
        "image": {
          "base_url": "https://commons.wikimedia.org/w/index.php?title=Special:Redirect/file/",
          "value": "Lefébure-Wély-young.jpg"
        }
      },
      {
        "id": "AaF6WQEA",
        "type": "item",
        "label": "Hans von Bülow",
        "description": "German conductor and pianist (1830–1894)",
        "image": {
          "base_url": "https://commons.wikimedia.org/w/index.php?title=Special:Redirect/file/",
          "value": "https://upload.wikimedia.org/wikipedia/commons/0/08/Hans_von_buelow.jpg"
        }
      },
      {
        "id": "KQYeWCdx",
        "type": "item",
        "label": "Franz Kullak",
        "description": "German composer (1844-1913)",
        "image": {
          "base_url": "https://commons.wikimedia.org/w/index.php?title=Special:Redirect/file/",
          "value": ""
        }
      },
      {
        "id": "ZBYUC5fa",
        "type": "item",
        "label": "August Wilhelmj",
        "description": "German violinist (1845–1908)",
        "image": {
          "base_url": "https://commons.wikimedia.org/w/index.php?title=Special:Redirect/file/",
          "value": "August_Wilhelmj.jpg"
        }
      },
      {
        "id": "5gAsc3pE",
        "type": "item",
        "label": "Alessandro Longo",
        "description": "Italian composer (1864–1945)",
        "image": {
          "base_url": "https://commons.wikimedia.org/w/index.php?title=Special:Redirect/file/",
          "value": "Aleslongo.jpg"
        }
      },
      {
        "id": "W5tLaHDf",
        "type": "item",
        "label": "Kaspar Fürstenau",
        "description": "German flautist (1772-1819)",
        "image": {
          "base_url": "https://commons.wikimedia.org/w/index.php?title=Special:Redirect/file/",
          "value": ""
        }
      },
      {
        "id": "aovZZUxK",
        "type": "item",
        "label": "Leopold Jansa",
        "description": "Czech violinist, music educator and composer (1795–1875)",
        "image": {
          "base_url": "https://commons.wikimedia.org/w/index.php?title=Special:Redirect/file/",
          "value": "https://upload.wikimedia.org/wikipedia/commons/9/9a/Leopold_Jansa.jpg"
        }
      },
      {
        "id": "ZchmW76w",
        "type": "item",
        "label": "Franz Alexander Pössinger",
        "description": "Austrian composer",
        "image": {
          "base_url": "https://commons.wikimedia.org/w/index.php?title=Special:Redirect/file/",
          "value": ""
        }
      },
      {
        "id": "2Sh2rJhV",
        "type": "item",
        "label": "Angelo Consolini",
        "description": "Italian composer (1859-1934)",
        "image": {
          "base_url": "https://commons.wikimedia.org/w/index.php?title=Special:Redirect/file/",
          "value": ""
        }
      },
      {
        "id": "4bJXjG2F",
        "type": "item",
        "label": "Georges Sporck",
        "description": "French composer (1870-1943)",
        "image": {
          "base_url": "https://commons.wikimedia.org/w/index.php?title=Special:Redirect/file/",
          "value": "Georges_Sporck.jpg"
        }
      },
      {
        "id": "5Ze3Bk9Z",
        "type": "item",
        "label": "Michel Folz",
        "description": "French composer and music arranger",
        "image": {
          "base_url": "https://commons.wikimedia.org/w/index.php?title=Special:Redirect/file/",
          "value": ""
        }
      },
      {
        "id": "EjvQ4EcD",
        "type": "item",
        "label": "Karl Schwencke",
        "description": "German pianist and composer",
        "image": {
          "base_url": "https://commons.wikimedia.org/w/index.php?title=Special:Redirect/file/",
          "value": "https://upload.wikimedia.org/wikipedia/commons/c/c3/PPN663943914_Carl_Schwencke_%281853%29.jpg"
        }
      },
      {
        "id": "JmsQ8D5i",
        "type": "item",
        "label": "Benoît-Constat Fauconier",
        "description": "French composer",
        "image": {
          "base_url": "https://commons.wikimedia.org/w/index.php?title=Special:Redirect/file/",
          "value": ""
        }
      },
      {
        "id": "6RuEaDAJ",
        "type": "item",
        "label": "Louis Dorus",
        "description": "French university teacher and flutist (1812-1896)",
        "image": {
          "base_url": "https://commons.wikimedia.org/w/index.php?title=Special:Redirect/file/",
          "value": "Louis_Dorus_1864.jpg"
        }
      },
      {
        "id": "d6k8Jy2L",
        "type": "item",
        "label": "Joseph Ghys",
        "description": "Belgian violinist (1801–1848)",
        "image": {
          "base_url": "https://commons.wikimedia.org/w/index.php?title=Special:Redirect/file/",
          "value": "Joseph_Ghys_1834.jpg"
        }
      },
      {
        "id": "GwzqZPkq",
        "type": "item",
        "label": "Gérard Nauwelaers",
        "description": "",
        "image": {
          "base_url": "https://commons.wikimedia.org/w/index.php?title=Special:Redirect/file/",
          "value": ""
        }
      },
      {
        "id": "9A7T4C3U",
        "type": "item",
        "label": "Franz Xaver Gleichauf",
        "description": "",
        "image": {
          "base_url": "https://commons.wikimedia.org/w/index.php?title=Special:Redirect/file/",
          "value": ""
        }
      },
      {
        "id": "RJrp7LF2",
        "type": "item",
        "label": "Vincenzo Gambaro",
        "description": "",
        "image": {
          "base_url": "https://commons.wikimedia.org/w/index.php?title=Special:Redirect/file/",
          "value": ""
        }
      },
      {
        "id": "VVgPhAqK",
        "type": "item",
        "label": "Gustav Zanger",
        "description": "",
        "image": {
          "base_url": "https://commons.wikimedia.org/w/index.php?title=Special:Redirect/file/",
          "value": ""
        }
      },
      {
        "id": "Xqd8kuF3",
        "type": "item",
        "label": "Eugen d'Albert",
        "description": "Scottish-born German pianist and composer (1864-1932)",
        "image": {
          "base_url": "https://commons.wikimedia.org/w/index.php?title=Special:Redirect/file/",
          "value": "Eugen_Francis_Charles_D'Albert_(before_1932)_-_Archivio_storico_Ricordi_FOTO001157.jpg"
        }
      },
      {
        "id": "SXsr2eC2",
        "type": "item",
        "label": "Henry Jacqmin",
        "description": "French composer and music arranger",
        "image": {
          "base_url": "https://commons.wikimedia.org/w/index.php?title=Special:Redirect/file/",
          "value": ""
        }
      },
      {
        "id": "2piRAHqK",
        "type": "item",
        "label": "Jos. Bouwens",
        "description": "",
        "image": {
          "base_url": "https://commons.wikimedia.org/w/index.php?title=Special:Redirect/file/",
          "value": ""
        }
      },
      {
        "id": "kFuM9vEH",
        "type": "item",
        "label": "L. Corret",
        "description": "French composer, horn player and music arranger",
        "image": {
          "base_url": "https://commons.wikimedia.org/w/index.php?title=Special:Redirect/file/",
          "value": ""
        }
      },
      {
        "id": "DknDehba",
        "type": "item",
        "label": "Andermann",
        "description": "",
        "image": {
          "base_url": "https://commons.wikimedia.org/w/index.php?title=Special:Redirect/file/",
          "value": ""
        }
      },
      {
        "id": "S63SGbw2",
        "type": "item",
        "label": "M. Gaultier",
        "description": "",
        "image": {
          "base_url": "https://commons.wikimedia.org/w/index.php?title=Special:Redirect/file/",
          "value": ""
        }
      },
      {
        "id": "DJXHHAks",
        "type": "item",
        "label": "P. Nacher",
        "description": "",
        "image": {
          "base_url": "https://commons.wikimedia.org/w/index.php?title=Special:Redirect/file/",
          "value": ""
        }
      },
      {
        "id": "XLmyCS7h",
        "type": "item",
        "label": "Daniel Hermann",
        "description": "",
        "image": {
          "base_url": "https://commons.wikimedia.org/w/index.php?title=Special:Redirect/file/",
          "value": ""
        }
      },
      {
        "id": "PNsdjaKx",
        "type": "item",
        "label": "Louis Lahou",
        "description": "Belgian arranger and music publisher",
        "image": {
          "base_url": "https://commons.wikimedia.org/w/index.php?title=Special:Redirect/file/",
          "value": ""
        }
      },
      {
        "id": "F9d5oekT",
        "type": "item",
        "label": "Johann Christian Bach",
        "description": "German composer (1735–1782)",
        "image": {
          "base_url": "https://commons.wikimedia.org/w/index.php?title=Special:Redirect/file/",
          "value": "Johann_Christian_Bach_by_Thomas_Gainsborough.jpg"
        }
      }
    ]
  },
  "resources": {
    "JSON": [
      {
        "type": "url",
        "base_url": "http://nicholascornia89.github.io/faam/json/",
        "value": "GSNsghRd.json"
      }
    ],
    "RDF": [
      {
        "type": "url",
        "base_url": "http://nicholascornia89.github.io/faam/rdf/",
        "value": "GSNsghRd.ttl"
      }
    ],
    "CSV": [
      {
        "type": "url",
        "base_url": "http://nicholascornia89.github.io/faam/csv/",
        "value": "GSNsghRd.csv"
      }
    ]
  }
}