{
  "id": "gvB7xdLy",
  "uuid_num": 76074998122018,
  "metadata": {
    "label": [
      {
        "type": "string",
        "value": "Charlotte Corday"
      },
      {
        "type": "string",
        "value": "Charlotte Corday"
      }
    ],
    "description": [
      {
        "type": "string",
        "value": "opera by Peter Benoit"
      }
    ],
    "object_type": [
      {
        "type": "schema",
        "value": "musical_work"
      }
    ],
    "id": [
      {
        "type": "id",
        "value": "gvB7xdLy"
      }
    ],
    "nodegoat_id": [
      {
        "type": "id",
        "value": "16002446"
      }
    ],
    "aliases": [
      {
        "type": "string",
        "value": "Charlotte Corday"
      }
    ],
    "qid": [
      {
        "type": "externalid",
        "value": "Q125389042",
        "base_url": "http://wwww.wikidata.org/entity/"
      }
    ]
  },
  "statements": {
    "IMSLP ID": [],
    "VIAF ID": [],
    "CPDL ID": [],
    "form of creative work": [
      {
        "type": "item",
        "value": "hxYumS2J",
        "label": "opera"
      },
      {
        "type": "item",
        "value": "5A76cUYt",
        "label": "drame lyrique"
      }
    ],
    "creator": [
      {
        "type": "item",
        "value": "73vECvez",
        "label": "Peter Benoit"
      }
    ],
    "adapted by": [],
    "based on": []
  },
  "cross-references": {},
  "resources": {}
}