{
  "id": "h7GA7wL7",
  "uuid_num": 76420993706771,
  "metadata": {
    "label": [
      {
        "type": "string",
        "value": "Cor mio deh non languire"
      }
    ],
    "description": [
      {
        "type": "string",
        "value": "madrigal attributed to Alessandro Scarlatti"
      }
    ],
    "aliases": [
      {
        "type": "string",
        "value": "Cor mio deh non languire"
      }
    ],
    "qid": [
      {
        "type": "externalid",
        "value": "Q124316713",
        "base_url": "http://wwww.wikidata.org/entity/",
        "label": "Cor mio deh non languire"
      }
    ],
    "object_type": [
      {
        "type": "schema",
        "value": "musical_work"
      }
    ],
    "id": [
      {
        "type": "id",
        "value": "h7GA7wL7"
      }
    ],
    "nodegoat_id": [
      {
        "type": "id",
        "value": "16002027"
      }
    ]
  },
  "statements": {
    "IMSLP ID": [],
    "VIAF ID": [],
    "CPDL ID": [],
    "form of creative work": [
      {
        "type": "item",
        "value": "EHXeMNgG",
        "label": "madrigal"
      }
    ],
    "creator": [
      {
        "type": "item",
        "value": "KzqrgycL",
        "label": "Alessandro Scarlatti"
      }
    ],
    "adapted by": [
      {
        "type": "item",
        "value": "jZ5Za9W2",
        "label": "Napoléon Joseph Ney"
      }
    ],
    "based on": []
  },
  "cross-references": {
    "manifestation": [
      {
        "id": "Mdtc39Ji",
        "type": "item",
        "label": "Recueil des morceaux de musique ancienne : executés aux concerts de la Sociéte de musique vocale religieuse et classique fondée a Paris en 1843 [...] sous la direction de Mr. le Prince de la Moskowa. [Deuxième volume, Nr 8-20]",
        "description": "",
        "thumb": {
          "base_url": "../assets/images/thumbs/",
          "value": "KMN-100549.gif"
        }
      },
      {
        "id": "Mdtc39Ji",
        "type": "item",
        "label": "Recueil des morceaux de musique ancienne : executés aux concerts de la Sociéte de musique vocale religieuse et classique fondée a Paris en 1843 [...] sous la direction de Mr. le Prince de la Moskowa. [Deuxième volume, Nr 8-20]",
        "description": "",
        "thumb": {
          "base_url": "../assets/images/thumbs/",
          "value": "KMN-100549.gif"
        }
      }
    ]
  },
  "resources": {
    "JSON": [
      {
        "type": "url",
        "base_url": "http://nicholascornia89.github.io/faam/json/",
        "value": "h7GA7wL7.json"
      }
    ],
    "RDF": [
      {
        "type": "url",
        "base_url": "http://nicholascornia89.github.io/faam/rdf/",
        "value": "h7GA7wL7.ttl"
      }
    ],
    "CSV": [
      {
        "type": "url",
        "base_url": "http://nicholascornia89.github.io/faam/csv/",
        "value": "h7GA7wL7.csv"
      }
    ]
  }
}