{
  "id": "isT2xDMy",
  "uuid_num": 79891477981645,
  "metadata": {
    "label": [
      {
        "type": "string",
        "value": "Goethe University Frankfurt"
      },
      {
        "type": "string",
        "value": "Goethe University Frankfurt"
      }
    ],
    "description": [
      {
        "type": "string",
        "value": "university in Frankfurt, Germany"
      }
    ],
    "object_type": [
      {
        "type": "schema",
        "value": "music_organization"
      }
    ],
    "id": [
      {
        "type": "id",
        "value": "isT2xDMy"
      }
    ],
    "nodegoat_id": [
      {
        "type": "id",
        "value": "15991070"
      }
    ],
    "qid": [
      {
        "type": "externalid",
        "value": "Q50662",
        "base_url": "http://wwww.wikidata.org/entity/",
        "label": "Goethe University Frankfurt"
      }
    ],
    "aliases": [
      {
        "type": "string",
        "value": "Johann Wolfgang Goethe-Universität Frankfurt am Main"
      },
      {
        "type": "string",
        "value": "University of Frankfurt am Main"
      },
      {
        "type": "string",
        "value": "Johann Wolfgang Goethe-Universitaet Frankfurt"
      },
      {
        "type": "string",
        "value": "Johann Wolfgang Goethe University"
      },
      {
        "type": "string",
        "value": "Johann Wolfgang Goethe University Frankfurt"
      },
      {
        "type": "string",
        "value": "Goethe University Frankfurt"
      }
    ]
  },
  "statements": {
    "place": [
      {
        "type": "item",
        "value": "SptwZTXr",
        "label": "Frankfurt"
      }
    ],
    "country": [
      {
        "type": "item",
        "value": "oDvJJJ7G",
        "label": "Germany"
      }
    ]
  },
  "cross-references": {
    "agent": [
      {
        "id": "XBjGQVps",
        "type": "item",
        "label": "Theodor W. Adorno",
        "description": "German philosopher, sociologist and theorist (1903–1969)",
        "image": {
          "base_url": "https://commons.wikimedia.org/w/index.php?title=Special:Redirect/file/",
          "value": "Theodor_W._Adorno.jpg"
        }
      },
      {
        "id": "oQCAcEAL",
        "type": "item",
        "label": "Hermann A. Korff",
        "description": "German literary historian (1882–1963)",
        "image": {
          "base_url": "https://commons.wikimedia.org/w/index.php?title=Special:Redirect/file/",
          "value": "Hermann_August_Korff_-_Jb._d._Sächs._Ak._d._Wiss.1963-65_(1967),_S._322.jpg"
        }
      },
      {
        "id": "XBjGQVps",
        "type": "item",
        "label": "Theodor W. Adorno",
        "description": "German philosopher, sociologist and theorist (1903–1969)",
        "image": {
          "base_url": "https://commons.wikimedia.org/w/index.php?title=Special:Redirect/file/",
          "value": "Theodor_W._Adorno.jpg"
        }
      }
    ]
  },
  "resources": {
    "JSON": [
      {
        "type": "url",
        "base_url": "http://nicholascornia89.github.io/faam/json/",
        "value": "isT2xDMy.json"
      }
    ],
    "RDF": [
      {
        "type": "url",
        "base_url": "http://nicholascornia89.github.io/faam/rdf/",
        "value": "isT2xDMy.ttl"
      }
    ],
    "CSV": [
      {
        "type": "url",
        "base_url": "http://nicholascornia89.github.io/faam/csv/",
        "value": "isT2xDMy.csv"
      }
    ]
  }
}