{
  "id": "LvevRK7u",
  "uuid_num": 36993784275534,
  "metadata": {
    "label": [
      {
        "type": "string",
        "value": "Mills College at Northeastern"
      }
    ],
    "description": [
      {
        "type": "string",
        "value": "liberal arts and sciences college located in Oakland, United States"
      }
    ],
    "aliases": [
      {
        "type": "string",
        "value": "Mills College"
      },
      {
        "type": "string",
        "value": "Mills College at Northeastern University"
      },
      {
        "type": "string",
        "value": "Northeastern University Oakland"
      },
      {
        "type": "string",
        "value": "Mills College at Northeastern University"
      }
    ],
    "qid": [
      {
        "type": "externalid",
        "value": "Q638859",
        "base_url": "http://wwww.wikidata.org/entity/",
        "label": "Mills College at Northeastern University"
      }
    ],
    "object_type": [
      {
        "type": "schema",
        "value": "music_organization"
      }
    ],
    "id": [
      {
        "type": "id",
        "value": "LvevRK7u"
      }
    ],
    "nodegoat_id": [
      {
        "type": "id",
        "value": "15991079"
      }
    ]
  },
  "statements": {
    "place": [
      {
        "type": "item",
        "value": "jBi6QCuf",
        "label": ""
      }
    ],
    "country": [
      {
        "type": "item",
        "value": "fiWxEeqn",
        "label": "United States of America"
      }
    ]
  },
  "cross-references": {
    "agent": [
      {
        "id": "JaKU2RAe",
        "type": "item",
        "label": "Darius Milhaud",
        "description": "French composer (1892–1974)",
        "image": {
          "base_url": "https://commons.wikimedia.org/w/index.php?title=Special:Redirect/file/",
          "value": "Darius_Milhaud_b_Meurisse_1923.jpg"
        }
      }
    ]
  },
  "resources": {
    "JSON": [
      {
        "type": "url",
        "base_url": "http://nicholascornia89.github.io/faam/json/",
        "value": "LvevRK7u.json"
      }
    ],
    "RDF": [
      {
        "type": "url",
        "base_url": "http://nicholascornia89.github.io/faam/rdf/",
        "value": "LvevRK7u.ttl"
      }
    ],
    "CSV": [
      {
        "type": "url",
        "base_url": "http://nicholascornia89.github.io/faam/csv/",
        "value": "LvevRK7u.csv"
      }
    ]
  }
}