{
  "id": "mFzbREKH",
  "uuid_num": 84540493424172,
  "metadata": {
    "label": [
      {
        "type": "string",
        "value": "Symphony No.86 in D major, Hob.I:86"
      }
    ],
    "description": [
      {
        "type": "string",
        "value": "symphony by Joseph Haydn"
      }
    ],
    "aliases": [
      {
        "type": "string",
        "value": "Symphony No. 86"
      }
    ],
    "qid": [
      {
        "type": "externalid",
        "value": "Q273132",
        "base_url": "http://wwww.wikidata.org/entity/",
        "label": "Symphony No. 86"
      }
    ],
    "object_type": [
      {
        "type": "schema",
        "value": "musical_work"
      }
    ],
    "id": [
      {
        "type": "id",
        "value": "mFzbREKH"
      }
    ],
    "nodegoat_id": [
      {
        "type": "id",
        "value": "16002434"
      }
    ]
  },
  "statements": {
    "IMSLP ID": [
      {
        "type": "externalid",
        "value": "Symphony No.86 in D major, Hob.I:86 (Haydn, Joseph)",
        "base_url": "https://imslp.org/wiki/",
        "label": "Symphony No.86 in D major, Hob.I:86 (Haydn, Joseph)"
      }
    ],
    "VIAF ID": [
      {
        "type": "externalid",
        "value": "176398844",
        "base_url": "https://viaf.org/viaf/",
        "label": "176398844"
      }
    ],
    "CPDL ID": [],
    "form of creative work": [
      {
        "type": "item",
        "value": "Zgsxtx6S",
        "label": "symphony"
      }
    ],
    "creator": [
      {
        "type": "item",
        "value": "jihjgQpH",
        "label": "Joseph Haydn"
      }
    ],
    "adapted by": [],
    "based on": []
  },
  "cross-references": {
    "manifestation": [
      {
        "id": "ciYNKvcf",
        "type": "item",
        "label": "Symphonie : à grand Orchestre",
        "description": "",
        "thumb": {
          "base_url": "../assets/images/thumbs/",
          "value": "KCG-000743756.gif"
        }
      }
    ]
  },
  "resources": {
    "JSON": [
      {
        "type": "url",
        "base_url": "http://nicholascornia89.github.io/faam/json/",
        "value": "mFzbREKH.json"
      }
    ],
    "RDF": [
      {
        "type": "url",
        "base_url": "http://nicholascornia89.github.io/faam/rdf/",
        "value": "mFzbREKH.ttl"
      }
    ],
    "CSV": [
      {
        "type": "url",
        "base_url": "http://nicholascornia89.github.io/faam/csv/",
        "value": "mFzbREKH.csv"
      }
    ]
  }
}