{
  "id": "MjKpT9w8",
  "uuid_num": 38559925704486,
  "metadata": {
    "label": [
      {
        "type": "string",
        "value": "adagio"
      },
      {
        "type": "string",
        "value": "adagio"
      }
    ],
    "description": [
      {
        "type": "string",
        "value": "musical tempo indication"
      }
    ],
    "object_type": [
      {
        "type": "schema",
        "value": "annotation_type"
      }
    ],
    "id": [
      {
        "type": "id",
        "value": "MjKpT9w8"
      }
    ],
    "nodegoat_id": [
      {
        "type": "id",
        "value": "15992208"
      }
    ],
    "qid": [
      {
        "type": "externalid",
        "value": "Q482153",
        "base_url": "http://wwww.wikidata.org/entity/",
        "label": "adagio"
      }
    ],
    "aliases": [
      {
        "type": "string",
        "value": "adagio"
      }
    ]
  },
  "statements": {
    "subclass of": [
      {
        "type": "item",
        "value": "WT9AcUBt",
        "label": "tempo"
      }
    ],
    "instance of": [
      {
        "type": "item",
        "value": "N2f5NSgz",
        "label": "musical notation"
      }
    ],
    "musical parameter": [
      {
        "type": "item",
        "value": "72sFir89",
        "label": "duration"
      }
    ],
    "used by": [
      {
        "type": "item",
        "value": "fkHJwpoD",
        "label": "composer"
      },
      {
        "type": "item",
        "value": "2ZAuwsSp",
        "label": "conductor"
      },
      {
        "type": "item",
        "value": "45qo3Fj3",
        "label": "music editor"
      }
    ]
  },
  "cross-references": {
    "manifestation": [
      {
        "id": "DXtyRBx2",
        "type": "item",
        "label": "Recueil des morceaux de musique ancienne exécutés aux concerts de la Société de musique vocale religieuse et classique, fondée à Paris en 1843..., sous la direction de Mr. le Prince de la Moskowa. Vol. 1 (nos 1-7)",
        "description": "",
        "thumb": {
          "base_url": "../assets/images/thumbs/",
          "value": "BNF-43090486d.gif"
        }
      }
    ]
  },
  "resources": {
    "JSON": [
      {
        "type": "url",
        "base_url": "http://nicholascornia89.github.io/faam/json/",
        "value": "MjKpT9w8.json"
      }
    ],
    "RDF": [
      {
        "type": "url",
        "base_url": "http://nicholascornia89.github.io/faam/rdf/",
        "value": "MjKpT9w8.ttl"
      }
    ],
    "CSV": [
      {
        "type": "url",
        "base_url": "http://nicholascornia89.github.io/faam/csv/",
        "value": "MjKpT9w8.csv"
      }
    ]
  }
}