{
  "id": "R48eNExS",
  "uuid_num": 45035229152265,
  "metadata": {
    "label": [
      {
        "type": "string",
        "value": "Brooklyn"
      }
    ],
    "description": [
      {
        "type": "string",
        "value": "borough of New York City, New York, United States"
      }
    ],
    "object_type": [
      {
        "type": "schema",
        "value": "city"
      }
    ],
    "id": [
      {
        "type": "id",
        "value": "R48eNExS"
      }
    ],
    "nodegoat_id": [
      {
        "type": "id",
        "value": "0"
      }
    ],
    "qid": [
      {
        "type": "externalid",
        "value": "Q18419",
        "base_url": "http://wwww.wikidata.org/entity/"
      }
    ],
    "aliases": [
      {
        "type": "string",
        "value": "Brooklyn"
      },
      {
        "type": "string",
        "value": "Brooklyn, New York City"
      },
      {
        "type": "string",
        "value": "Brooklyn, New York"
      },
      {
        "type": "string",
        "value": "Brooklyn, New York City, New York"
      },
      {
        "type": "string",
        "value": "Brooklyn, NY"
      }
    ]
  },
  "statements": {
    "GeoNames ID": [
      {
        "type": "externalid",
        "value": "5110302",
        "base_url": "https://www.geonames.org/",
        "label": "5110302"
      }
    ]
  },
  "cross-references": {},
  "resources": {}
}