{
  "id": "Y59WH8ZP",
  "uuid_num": 58754324349141,
  "metadata": {
    "label": [
      {
        "type": "string",
        "value": "Kuldīga"
      }
    ],
    "description": [
      {
        "type": "string",
        "value": "city in Latvia"
      }
    ],
    "aliases": [
      {
        "type": "string",
        "value": ""
      }
    ],
    "qid": [
      {
        "type": "externalid",
        "value": "Q155281",
        "base_url": "http://wwww.wikidata.org/entity/",
        "label": "Kuldīga"
      }
    ],
    "object_type": [
      {
        "type": "schema",
        "value": "city"
      }
    ],
    "id": [
      {
        "type": "id",
        "value": "Y59WH8ZP"
      }
    ],
    "nodegoat_id": [
      {
        "type": "id",
        "value": "0"
      }
    ]
  },
  "statements": {
    "GeoNames ID": [
      {
        "type": "externalid",
        "value": "11352717",
        "base_url": "https://www.geonames.org/",
        "label": "11352717"
      }
    ],
    "country": [
      {
        "type": "externalid",
        "value": "Q211",
        "base_url": "",
        "label": "Latvia"
      }
    ]
  },
  "cross-references": {
    "agent": [
      {
        "id": "7FTvdvo6",
        "type": "item",
        "label": "Karl Davydov",
        "description": "Russian composer (1838–1889)",
        "image": {
          "base_url": "https://commons.wikimedia.org/w/index.php?title=Special:Redirect/file/",
          "value": "Davidov-Karl.jpg"
        }
      }
    ]
  },
  "resources": {
    "JSON": [
      {
        "type": "url",
        "base_url": "http://nicholascornia89.github.io/faam/json/",
        "value": "Y59WH8ZP.json"
      }
    ],
    "RDF": [
      {
        "type": "url",
        "base_url": "http://nicholascornia89.github.io/faam/rdf/",
        "value": "Y59WH8ZP.ttl"
      }
    ],
    "CSV": [
      {
        "type": "url",
        "base_url": "http://nicholascornia89.github.io/faam/csv/",
        "value": "Y59WH8ZP.csv"
      }
    ]
  }
}