{
  "id": "ZGMagNYo",
  "uuid_num": 61093749595653,
  "metadata": {
    "label": [
      {
        "type": "string",
        "value": "transposition"
      },
      {
        "type": "string",
        "value": "transposition"
      }
    ],
    "description": [
      {
        "type": "string",
        "value": "operation in music of moving multiple notes by the same interval"
      }
    ],
    "object_type": [
      {
        "type": "schema",
        "value": "annotation_type"
      }
    ],
    "id": [
      {
        "type": "id",
        "value": "ZGMagNYo"
      }
    ],
    "nodegoat_id": [
      {
        "type": "id",
        "value": "15992190"
      }
    ],
    "qid": [
      {
        "type": "externalid",
        "value": "Q815323",
        "base_url": "http://wwww.wikidata.org/entity/"
      }
    ],
    "aliases": [
      {
        "type": "string",
        "value": "pitch translation invariance"
      },
      {
        "type": "string",
        "value": "transposition (music)"
      },
      {
        "type": "string",
        "value": "music transposition"
      },
      {
        "type": "string",
        "value": "transposition of music"
      },
      {
        "type": "string",
        "value": "transposing music"
      },
      {
        "type": "string",
        "value": "musical transposition"
      },
      {
        "type": "string",
        "value": "transposition"
      }
    ]
  },
  "statements": {
    "subclass of": [
      {
        "type": "item",
        "value": "4TFDsVbk",
        "label": ""
      }
    ],
    "instance of": [
      {
        "type": "item",
        "value": "BH3QSV35",
        "label": "musical concept"
      }
    ],
    "musical parameter": [
      {
        "type": "item",
        "value": "Cf64Khds",
        "label": "pitch"
      }
    ],
    "used by": [
      {
        "type": "item",
        "value": "2ZAuwsSp",
        "label": "conductor"
      },
      {
        "type": "item",
        "value": "45qo3Fj3",
        "label": "music editor"
      },
      {
        "type": "item",
        "value": "GoiPpGap",
        "label": "performing artist"
      }
    ]
  },
  "cross-references": {},
  "resources": {}
}